iugu/__init__.py
iugu/action.py
iugu/customer.py
iugu/exception.py
iugu/invoice.py
iugu/iuguapi.py
iugu/marketplace.py
iugu/plan.py
iugu/subscription.py
iugu/token.py
iugu/transfer.py
iugu/version.py
iugu_trustcode-0.1.3.2.dist-info/LICENSE.txt
iugu_trustcode-0.1.3.2.dist-info/METADATA
iugu_trustcode-0.1.3.2.dist-info/WHEEL
iugu_trustcode-0.1.3.2.dist-info/top_level.txt
iugu_trustcode-0.1.3.2.dist-info/RECORD
