Metadata-Version: 1.1
Name: iugu-trustcode
Version: 0.1.3.2
Summary: The Iugu provides a Python REST APIs to create, process and manage payments.
Home-page: https://github.com/iugu/iugu-python
Author: Felipe Tomaz, Arthur Furlan
Author-email: gmail@felipetomaz.com, afurlan@afurlan.org
License: MIT
Keywords: iugu,rest,payment
Platform: UNKNOWN
Classifier: Intended Audience :: Developers
Classifier: Natural Language :: English
Classifier: Operating System :: OS Independent
Classifier: Programming Language :: Python
Classifier: Programming Language :: Python :: 2
Classifier: Programming Language :: Python :: 2.6
Classifier: Programming Language :: Python :: 2.7
Classifier: Topic :: Software Development :: Libraries :: Python Modules
